pythonnative/__init__.py
pythonnative/activity_indicator_view.py
pythonnative/button.py
pythonnative/collection_view.py
pythonnative/date_picker.py
pythonnative/image_view.py
pythonnative/label.py
pythonnative/list_view.py
pythonnative/material_activity_indicator_view.py
pythonnative/material_bottom_navigation_view.py
pythonnative/material_button.py
pythonnative/material_date_picker.py
pythonnative/material_progress_view.py
pythonnative/material_search_bar.py
pythonnative/material_switch.py
pythonnative/material_time_picker.py
pythonnative/material_toolbar.py
pythonnative/page.py
pythonnative/picker_view.py
pythonnative/progress_view.py
pythonnative/scroll_view.py
pythonnative/search_bar.py
pythonnative/stack_view.py
pythonnative/switch.py
pythonnative/text_field.py
pythonnative/text_view.py
pythonnative/time_picker.py
pythonnative/utils.py
pythonnative/view.py
pythonnative/web_view.py
pythonnative/cli/__init__.py
pythonnative/cli/pn.py
pythonnative/templates/android_template/build.gradle
pythonnative/templates/android_template/gradle.properties
pythonnative/templates/android_template/gradlew
pythonnative/templates/android_template/gradlew.bat
pythonnative/templates/android_template/settings.gradle
pythonnative/templates/android_template/app/build.gradle
pythonnative/templates/android_template/app/proguard-rules.pro
pythonnative/templates/android_template/app/src/androidTest/java/com/pythonnative/android_template/ExampleInstrumentedTest.kt
pythonnative/templates/android_template/app/src/main/AndroidManifest.xml
pythonnative/templates/android_template/app/src/main/java/com/pythonnative/android_template/MainActivity.kt
pythonnative/templates/android_template/app/src/main/java/com/pythonnative/android_template/Navigator.kt
pythonnative/templates/android_template/app/src/main/java/com/pythonnative/android_template/PageFragment.kt
pythonnative/templates/android_template/app/src/main/res/drawable/ic_launcher_background.xml
pythonnative-0.3.0.dist-info/licenses/LICENSE
pythonnative-0.3.0.dist-info/METADATA
pythonnative-0.3.0.dist-info/WHEEL
pythonnative-0.3.0.dist-info/entry_points.txt
pythonnative-0.3.0.dist-info/top_level.txt
pythonnative-0.3.0.dist-info/RECORD
