Metadata-Version: 2.4
Name: pythonnative
Version: 0.3.0
Summary: Cross-platform native UI toolkit for Android and iOS
Author: Owen Carey
License: MIT License
Project-URL: Homepage, https://github.com/pythonnative/pythonnative
Project-URL: Repository, https://github.com/pythonnative/pythonnative
Project-URL: Issues, https://github.com/pythonnative/pythonnative/issues
Project-URL: Documentation, https://docs.pythonnative.com/
Classifier: Development Status :: 2 - Pre-Alpha
Classifier: Intended Audience :: Developers
Classifier: License :: OSI Approved :: MIT License
Classifier: Programming Language :: Python :: 3
Classifier: Programming Language :: Python :: 3 :: Only
Classifier: Programming Language :: Python :: 3.9
Classifier: Programming Language :: Python :: 3.10
Classifier: Programming Language :: Python :: 3.11
Classifier: Programming Language :: Python :: 3.12
Classifier: Topic :: Software Development :: User Interfaces
Requires-Python: >=3.9
License-File: LICENSE
Requires-Dist: requests>=2.31.0
Provides-Extra: ios
Requires-Dist: rubicon-objc<0.5.0,>=0.4.6; extra == "ios"
Provides-Extra: docs
Requires-Dist: mkdocs>=1.5; extra == "docs"
Requires-Dist: mkdocs-material[imaging]>=9.5; extra == "docs"
Requires-Dist: mkdocstrings[python]>=0.24; extra == "docs"
Provides-Extra: dev
Requires-Dist: black>=24.0; extra == "dev"
Requires-Dist: ruff>=0.5; extra == "dev"
Requires-Dist: mypy>=1.10; extra == "dev"
Requires-Dist: pytest>=8.0; extra == "dev"
Provides-Extra: ci
Requires-Dist: black>=24.0; extra == "ci"
Requires-Dist: ruff>=0.5; extra == "ci"
Requires-Dist: mypy>=1.10; extra == "ci"
Requires-Dist: pytest>=8.0; extra == "ci"
Dynamic: license-file
